ALU.v
/////////////////////////////////////////
// 7 Op ALU Simulation
/////////////////////////////////////////

module ALU (clk, A, B, Opin, result, zero);

// var declaration 

input clk;

input[31:0] A;
input[31:0] B;
input[3:0] Opin;
output[31:0] result;
output zero;

reg[3:0] Opcode;
reg[31:0] result;
reg zero;
// parameters

// Logic params

parameter AND   = 4'b0100;
parameter OR    = 4'b0101;
parameter NOR   = 4'b0111;
parameter XOR   = 4'b0110;

// Arithmetic params

parameter add   = 4'b0000;
parameter sub   = 4'b0010;
parameter slt   = 4'b1010;

// Zero params
parameter zeronum = 32'b0;

// ALU Logic
always @(posedge clk or negedge clk) 
    begin
        if (result == zeronum)  zero = 1'b1;
        else                    zero = 1'b0;
    end

always @(posedge clk)
    begin
        Opcode <= Opin;
        case (Opcode)
            AND:    result <= A & B;
            OR:     result <= A | B;
            NOR:    result <= A ~| B;
            XOR:    result <= A ^ B;
            add:    result <= A + B;
            sub:    result <= A - B;

            slt:    result = (A<B) ? 1'b1 : 1'b0;

            default: result <= zeronum;
        endcase        
    end
    
endmodule

ALU_tb.v
`timescale 1s/1ns
`include "ALU.v"

module ALU_tb;
//var declaration
    reg clk;
    reg[31:0] A;
    reg[31:0] B;
    reg[3:0] Opin;

    wire[31:0] result;
    wire zero;

// parameters

// Logic params

parameter AND   = 4'b0100;
parameter OR    = 4'b0101;
parameter NOR   = 4'b0111;
parameter XOR   = 4'b0110;

// Arithmetic params

parameter add   = 4'b0000;
parameter sub   = 4'b0010;
parameter slt   = 4'b1010;

//device under test
ALU dut(clk, A, B, Opin, result, zero);

initial begin
    $dumpfile("ALU.vcd");
    $dumpvars(0, ALU_tb);
//1s clock
    clk = 0;
    forever #0.5 clk=~clk;
end

initial begin
//inputs
    A = 32'b00000000000000000000000000011011;
    B = 32'b00000000000000000000000000011011;
end

initial begin
//Op inputs
    Opin = AND; #2
    Opin = OR; #2
    Opin = NOR; #2
    Opin = XOR; #2
    Opin = add; #2
    Opin = sub; #2
    Opin = slt; #2
    #4
    $finish;
end

endmodule

ALU.vcd
$date
	Wed Oct  2 16:39:27 2019
$end
$version
	Icarus Verilog
$end
$timescale
	1ns
$end
$scope module ALU_tb $end
$var wire 1 ! zero $end
$var wire 32 " result [31:0] $end
$var reg 32 # A [31:0] $end
$var reg 32 $ B [31:0] $end
$var reg 4 % Opin [3:0] $end
$var reg 1 & clk $end
$scope module dut $end
$var wire 32 ' A [31:0] $end
$var wire 32 ( B [31:0] $end
$var wire 4 ) Opin [3:0] $end
$var wire 1 & clk $end
$var reg 4 * Opcode [3:0] $end
$var reg 32 + result [31:0] $end
$var reg 1 ! zero $end
$upscope $end
$upscope $end
$enddefinitions $end
#0
$dumpvars
bx +
bx *
b100 )
b11011 (
b11011 '
0&
b100 %
b11011 $
b11011 #
bx "
0!
$end
#500000000
b100 *
1&
#1000000000
0&
#1500000000
b11011 "
b11011 +
1&
#2000000000
0&
b101 %
b101 )
#2500000000
b101 *
1&
#3000000000
0&
#3500000000
1&
#4000000000
0&
b111 %
b111 )
#4500000000
b111 *
1&
#5000000000
0&
#5500000000
b11111111111111111111111111100100 "
b11111111111111111111111111100100 +
1&
#6000000000
0&
b110 %
b110 )
#6500000000
b110 *
1&
#7000000000
0&
#7500000000
b0 "
b0 +
1&
#8000000000
1!
0&
b0 %
b0 )
#8500000000
b0 *
1&
#9000000000
0&
#9500000000
b110110 "
b110110 +
1&
#10000000000
0!
0&
b10 %
b10 )
#10500000000
b10 *
1&
#11000000000
0&
#11500000000
b0 "
b0 +
1&
#12000000000
1!
0&
b1010 %
b1010 )
#12500000000
b1010 *
1&
