ALU.v
/////////////////////////////////////////
// 7 Op ALU Simulation
/////////////////////////////////////////

module ALU (clk, reset, A, B, Opin, result, zero);

// var declaration 

input clk;
input reset;

input[31:0] A;
input[31:0] B;
input[3:0] Opin;
output[31:0] result;
output zero;

reg[3:0] Opcode;
reg[31:0] result;
reg zero;
// parameters

// Logic params

parameter AND   = 0100;
parameter OR    = 0101;
parameter NOR   = 0111;
parameter XOR   = 0110;

// Arithmetic params

parameter add   = 0000;
parameter sub   = 0010;
parameter slt   = 1010;

// ALU Logic

always @(posedge clk)
    begin
        Opcode <= Opin;
        case (Opcode)
            AND:    result = A & B;
            OR:     result = A | B;
            NOR:    result = ~(A & B);
            XOR:    result = A ^ B;
            add:    result = A + B;
            sub:    result = A - B;
            slt:
            default: result = 32'b00000000000000000000000000000000;
        endcase
        if 
    end
endmodule

ALU_tb.v
`timescale 1s/1ns
`include "ALU.v"

module ALU_tb;
    reg clk;
    reg reset;
    reg[31:0] A;
    reg[31:0] B;
    reg[3:0] Opin;

    wire[31:0] result;
    wire zero;
ALU dut(clk, reset, A, B, Opin, result, zero);

initial begin
    $dumpfile("ALU.vcd");
    $dumpvars(0, ALU_tb);
    clk = 0;
    forever #0.5 clk=~clk;
end
initial begin
    A = 32'b00000000000000000000000000011011;
    B = 32'b00000000000000000000000000101110;
end
initial begin
    Opin = 4'b0000; #2
    Opin = 4'b0100; #2
    Opin = 4'b0111; #2
    Opin = 4'b0010; #2
    Opin = 4'b1010; #2
    $finish;
end

endmodule

ALU.vcd
$date
	Mon Sep 30 21:14:43 2019
$end
$version
	Icarus Verilog
$end
$timescale
	1ns
$end
$scope module ALU_tb $end
$var wire 1 ! zero $end
$var wire 32 " result [31:0] $end
$var reg 32 # A [31:0] $end
$var reg 32 $ B [31:0] $end
$var reg 4 % Opin [3:0] $end
$var reg 1 & clk $end
$var reg 1 ' reset $end
$scope module dut $end
$var wire 32 ( A [31:0] $end
$var wire 32 ) B [31:0] $end
$var wire 4 * Opin [3:0] $end
$var wire 1 & clk $end
$var wire 1 ' reset $end
$var reg 4 + Opcode [3:0] $end
$var reg 32 , result [31:0] $end
$var reg 1 ! zero $end
$upscope $end
$upscope $end
$enddefinitions $end
#0
$dumpvars
bx ,
bx +
b0 *
b101110 )
b11011 (
x'
0&
b0 %
b101110 $
b11011 #
bx "
x!
$end
#500000000
b0 "
b0 ,
b0 +
0!
1&
#1000000000
0&
#1500000000
b1001001 "
b1001001 ,
1!
1&
#2000000000
0&
b100 %
b100 *
#2500000000
b100 +
0!
1&
#3000000000
0&
#3500000000
b0 "
b0 ,
1&
#4000000000
0&
b111 %
b111 *
#4500000000
b111 +
1!
1&
#5000000000
0&
#5500000000
1&
#6000000000
0&
b10 %
b10 *
#6500000000
b10 +
1&
#7000000000
0&
#7500000000
1&
#8000000000
0&
b1010 %
b1010 *
#8500000000
b1010 +
1&
#9000000000
0&
#9500000000
b11111111111111111111111111101101 "
b11111111111111111111111111101101 ,
1&
