ALU.v
/////////////////////////////////////////
// 7 Op ALU Simulation
/////////////////////////////////////////

module ALU (clk, A, B, Opin, result, zero);

// var declaration 

input clk;

input[31:0] A;
input[31:0] B;
input[3:0] Opin;
output[31:0] result;
output zero;

reg[3:0] Opcode;
reg[31:0] result;
reg zero;
// parameters

// Logic params

parameter AND   = 4'b0100;
parameter OR    = 4'b0101;
parameter NOR   = 4'b0111;
parameter XOR   = 4'b0110;

// Arithmetic params

parameter add   = 4'b0000;
parameter sub   = 4'b0010;
parameter slt   = 4'b1010;

// Zero params
parameter zeronum = 32'b0;

// ALU Logic
always @(posedge clk or negedge clk) 
    begin
        if (result == zeronum)  zero = 1'b1;
        else                    zero = 1'b0;
    end

always @(posedge clk)
    begin
        Opcode <= Opin;
        case (Opcode)
            AND:    result <= A & B;
            OR:     result <= A | B;
            NOR:    result <= A ~| B;
            XOR:    result <= A ^ B;
            add:    result <= A + B;
            sub:    result <= A - B;

            slt:    result = (A<B) ? 1'b1 : 1'b0;

            default: result <= zeronum;
        endcase        
    end
    
endmodule

ALU_test.v
`timescale 1ns / 1ps
`include "ALU.v"
////////////////////////////////////////////////////////////////////////////////
// Tool versions:  
// Description: Simple testbench to test the ALU
//
//
// Dependencies:
// 
// Revision:
// Revision 0.01 - File Created
// Additional Comments:
// 
////////////////////////////////////////////////////////////////////////////////

module ALU_test;

	// Inputs
   reg [31:0]	A;
   reg [31:0]	B;
   reg [3:0]	Opin;

   // Outputs
   wire [31:0]	result;
   wire			zero;

   // Test clock 
   reg			clk; // in this version we do not really need the clock

   // Expected outputs
   reg [31:0]	exp_result;
   wire			exp_zero;

   // Vector and Error counts
   reg [10:0]	vec_cnt, err_cnt;
   reg [99:0]	testvec[0:12];

   // TO DO:
   // Define an array called 'testvec' that is wide enough to hold the inputs:
   //   Opin, a, b 
  
	//
   // and the expected output
   //   exp_result
	//
   // for each testcase.
   // Note: we will not store 'exp_zero' in this array.

 

	ALU dut(clk, A, B, Opin, result, zero);

   // The test clock generation
    always				// process always triggers
	begin
		clk=1; #50;		// clk is 1 for 50 ns 
		clk=0; #50;		// clk is 0 for 50 ns
	end					// generate a 100 ns clock


   // Initialization
   	initial
	begin 
	$dumpfile("ALU2.vcd");
    $dumpvars(0, ALU_test);
	$readmemh("testvectors_hex.txt", testvec, 0, 11);
		// TO DO:
		// Read the content of the file testvectors_hex.txt into the 
		// array testvec. The file contains values in hexadecimal format

	err_cnt=0; // number of errors
	vec_cnt=0; // number of vectors
   	end
	   
   // TO DO:
   // calculate the value of 'exp_zero' from the 'exp_result'
   // 
   assign exp_zero = (result==0) ? 1'b1 : 1'b0;
   
   // Tests
	always @ (posedge clk)		// trigger with the test clock
	begin
		// Wait 20 ns, so that we can safely apply the inputs
		#20; 
		
		// Assign the signals from the testvec array
		{Opin,A,B,exp_result}= testvec[vec_cnt]; 

		// Wait another 60ns after which we will be at 80ns
		#181; // tiempo minimo para que se sincronizen los valores.
	
		// Check if output is not what we expect to see
		if ((result !== exp_result) | (zero !== exp_zero))
		begin                                         
			// Display message
			$display("Error at %5d ns: Opin %b a=%h b=%h", $time, Opin,A,B);	// %h displays hex
			$display("       %h (%h expected)",result,exp_result);
			$display(" Zero: %b (%b expected)",zero,exp_zero);							// %b displays binary
			err_cnt = err_cnt + 1;																// increment error count
		end

		vec_cnt = vec_cnt + 1;																	// next vector
	
		// We use === so that we can also test for X
		if ((testvec[vec_cnt][99:96] === 4'bxxxx))
		begin
			// End of test, no more entries...
			$display ("%d tests completed with %d errors", vec_cnt, err_cnt);
			
			// Wait so that we can see the last result
			#20; 
			
			// Terminate simulation
			$finish;
		end
	end

   // TO DO:

   // Instantiate the Unit Under Test (UUT)
   
endmodule

ALU2.vcd
$date
	Thu Oct  3 01:34:36 2019
$end
$version
	Icarus Verilog
$end
$timescale
	1ps
$end
$scope module ALU_test $end
$var wire 1 ! zero $end
$var wire 32 " result [31:0] $end
$var wire 1 # exp_zero $end
$var reg 32 $ A [31:0] $end
$var reg 32 % B [31:0] $end
$var reg 4 & Opin [3:0] $end
$var reg 1 ' clk $end
$var reg 11 ( err_cnt [10:0] $end
$var reg 32 ) exp_result [31:0] $end
$var reg 11 * vec_cnt [10:0] $end
$scope module dut $end
$var wire 32 + A [31:0] $end
$var wire 32 , B [31:0] $end
$var wire 4 - Opin [3:0] $end
$var wire 1 ' clk $end
$var reg 4 . Opcode [3:0] $end
$var reg 32 / result [31:0] $end
$var reg 1 ! zero $end
$upscope $end
$upscope $end
$enddefinitions $end
#0
$dumpvars
b0 /
bx .
bx -
bx ,
bx +
b0 *
bx )
b0 (
1'
bx &
bx %
bx $
1#
b0 "
0!
$end
#50000
1!
0'
#100000
1'
#120000
b0 &
b0 -
b0 $
b0 +
b0 %
b0 ,
b0 )
#150000
0'
#200000
b0 .
1'
#250000
0'
#300000
1'
#301000
b1 *
#350000
0'
#400000
1'
#420000
b1 $
b1 +
b1 )
#450000
0'
#500000
0#
b1 "
b1 /
1'
#550000
0!
0'
#600000
1'
#601000
b10 *
#650000
0'
#700000
1'
#720000
b11111111111111111111111111111111 %
b11111111111111111111111111111111 ,
b0 )
#750000
0'
#800000
1#
b0 "
b0 /
1'
#850000
1!
0'
#900000
1'
#901000
b11 *
#950000
0'
#1000000
1'
#1020000
b10 &
b10 -
b0 $
b0 +
b1 %
b1 ,
b11111111111111111111111111111111 )
#1050000
0'
#1100000
0#
b1 "
b1 /
b10 .
1'
#1150000
0!
0'
#1200000
b11111111111111111111111111111111 "
b11111111111111111111111111111111 /
1'
#1201000
b100 *
#1250000
0'
#1300000
1'
#1320000
b100 &
b100 -
b1001000110100010101100111 $
b1001000110100010101100111 +
b10001001101010111100110111101111 %
b10001001101010111100110111101111 ,
b1001000110100010101100111 )
#1350000
0'
#1400000
b1110111011101110111011101111000 "
b1110111011101110111011101111000 /
b100 .
1'
#1450000
0'
#1500000
b1001000110100010101100111 "
b1001000110100010101100111 /
1'
#1501000
b101 *
#1550000
0'
#1600000
1'
#1620000
b101 &
b101 -
b10001001101010111100110111101111 )
#1650000
0'
#1700000
b101 .
1'
#1750000
0'
#1800000
b10001001101010111100110111101111 "
b10001001101010111100110111101111 /
1'
#1801000
b110 *
#1850000
0'
#1900000
1'
#1920000
b110 &
b110 -
b10001000100010001000100010001000 )
#1950000
0'
#2000000
b110 .
1'
#2050000
0'
#2100000
b10001000100010001000100010001000 "
b10001000100010001000100010001000 /
1'
#2101000
b111 *
#2150000
0'
#2200000
1'
#2220000
b111 &
b111 -
b0 $
b0 +
b11110000101001011110000110000111 %
b11110000101001011110000110000111 ,
b1111010110100001111001111000 )
#2250000
0'
#2300000
b11110000101001011110000110000111 "
b11110000101001011110000110000111 /
b111 .
1'
#2350000
0'
#2400000
b1111010110100001111001111000 "
b1111010110100001111001111000 /
1'
#2401000
b1000 *
#2450000
0'
#2500000
1'
#2520000
b1010 &
b1010 -
b100000000 $
b100000000 +
b11111111111111111111111111101111 %
b11111111111111111111111111101111 ,
b1 )
#2550000
0'
#2600000
b10000 "
b10000 /
b1010 .
1'
#2650000
0'
#2700000
b1 "
b1 /
1'
#2701000
b1001 *
#2750000
0'
#2800000
1'
#2820000
b1000000000000 %
b1000000000000 ,
#2850000
0'
#2900000
1'
#2950000
0'
#3000000
1'
#3001000
b1010 *
#3050000
0'
#3100000
1'
#3120000
b100000000 %
b100000000 ,
b0 )
#3150000
0'
#3200000
1#
b0 "
b0 /
1'
#3250000
1!
0'
#3300000
1'
#3301000
b1011 *
#3350000
0'
#3400000
1'
#3420000
b111111111 $
b111111111 +
#3450000
0'
#3500000
1'
#3550000
0'
#3600000
1'
#3601000
b1100 *
